{"code": 0, "message": "0", "ttl": 1, "data": {"config": {"id": 246, "type": "weekly_selected", "number": 241, "subject": "史上最强电路维修", "stime": 1698336000, "etime": 1698940799, "status": 2, "name": "2023第241期 10.27 - 11.02", "label": "第241期(1103更新)", "hint": "", "color": 0, "cover": "", "share_title": "史上最强电路维修丨每周必看第241期", "share_subtitle": "家中四处漏电的背后竟然有离奇原因？600万网友见证UP主拯救一栋楼！", "media_id": 2564871888}, "reminder": "每周五晚18:00更新", "list": [{"aid": 920303944, "videos": 1, "tid": 232, "tname": "科工机械", "copyright": 1, "pic": "http://i0.hdslb.com/bfs/archive/2c6a79b819a34062494d621aff450a0286febcc3.jpg", "title": "严重的电路故障往往都有含金量较高的原因", "pubdate": 1698578679, "ctime": 1698578679, "desc": "-", "state": 0, "duration": 766, "rights": {"bp": 0, "elec": 0, "download": 0, "movie": 0, "pay": 0, "hd5": 0, "no_reprint": 1, "autoplay": 1, "ugc_pay": 0, "is_cooperation": 0, "ugc_pay_preview": 0, "no_background": 0, "arc_pay": 0, "pay_free_watch": 0}, "owner": {"mid": 1985127693, "name": "城阳电工电路", "face": "https://i0.hdslb.com/bfs/face/faae5daababbf652d97faedab1a25d78b654fc44.jpg"}, "stat": {"aid": 920303944, "view": 11340462, "danmaku": 37884, "reply": 21498, "favorite": 259757, "coin": 542227, "share": 216192, "now_rank": 0, "his_rank": 1, "like": 1485434, "dislike": 0, "vt": 0, "vv": 11340462}, "dynamic": "", "cid": 1315053235, "dimension": {"width": 720, "height": 1280, "rotate": 0}, "short_link_v2": "https://b23.tv/BV1Mu4y1J73V", "up_from_v2": 35, "first_frame": "http://i1.hdslb.com/bfs/storyff/n231029sa2a80imlh4g2or1u091k4m64_firsti.jpg", "pub_location": "山东", "cover43": "", "bvid": "BV1Mu4y1J73V", "season_type": 0, "is_ogv": false, "ogv_info": null, "enable_vt": 0, "ai_rcmd": null, "rcmd_reason": "史上最强电工，凭一己之力拯救了一栋楼！"}, {"aid": 875299665, "videos": 1, "tid": 138, "tname": "搞笑", "copyright": 1, "pic": "http://i0.hdslb.com/bfs/archive/64ed7f5f04a31498f185695c8a6298eefc924ccd.jpg", "title": "史上最炫团建", "pubdate": 1698742800, "ctime": 1698735127, "desc": "美食区一鸽，前来觐见！\n感谢关注！\n感谢点赞、投币、收藏、转发！\n一定要看到最后！", "state": 0, "duration": 1612, "mission_id": 1703706, "rights": {"bp": 0, "elec": 0, "download": 0, "movie": 0, "pay": 0, "hd5": 0, "no_reprint": 1, "autoplay": 1, "ugc_pay": 0, "is_cooperation": 1, "ugc_pay_preview": 0, "no_background": 0, "arc_pay": 0, "pay_free_watch": 0}, "owner": {"mid": 446430908, "name": "小傲想睡觉", "face": "https://i2.hdslb.com/bfs/face/ff50c7ace4ffc66eac2bafcca8b91ca29cd80ad5.jpg"}, "stat": {"aid": 875299665, "view": 9964581, "danmaku": 72020, "reply": 7513, "favorite": 200447, "coin": 315333, "share": 10053, "now_rank": 0, "his_rank": 1, "like": 526702, "dislike": 0, "vt": 0, "vv": 9964581}, "dynamic": "史上最炫团建", "cid": 1318477726, "dimension": {"width": 1920, "height": 1080, "rotate": 0}, "short_link_v2": "https://b23.tv/BV1EN4y167uS", "first_frame": "http://i0.hdslb.com/bfs/storyff/n231101sa5a1p7xmyxlw91w4osax3iui_firsti.jpg", "pub_location": "上海", "cover43": "", "bvid": "BV1EN4y167uS", "season_type": 0, "is_ogv": false, "ogv_info": null, "enable_vt": 0, "ai_rcmd": null, "rcmd_reason": "员工自费团建？"}, {"aid": 832871413, "videos": 2, "tid": 256, "tname": "短片", "copyright": 1, "pic": "http://i0.hdslb.com/bfs/archive/5d66b2ddf4d914468b99bfe3ab63391d09733681.jpg", "title": "在自己婚礼上放《大型纪录片》，五星上将麦克阿瑟倾情出演", "pubdate": 1698598893, "ctime": 1698598893, "desc": "2023.10.28结婚咯", "state": 0, "duration": 317, "mission_id": 1693004, "rights": {"bp": 0, "elec": 0, "download": 0, "movie": 0, "pay": 0, "hd5": 0, "no_reprint": 1, "autoplay": 1, "ugc_pay": 0, "is_cooperation": 0, "ugc_pay_preview": 0, "no_background": 0, "arc_pay": 0, "pay_free_watch": 0}, "owner": {"mid": 676251275, "name": "之涵大战L大超", "face": "https://i2.hdslb.com/bfs/face/c2ae115f5a238ccc5f4bbe175087975ceb925fd5.jpg"}, "stat": {"aid": 832871413, "view": 6589277, "danmaku": 5980, "reply": 8380, "favorite": 61388, "coin": 196362, "share": 33066, "now_rank": 0, "his_rank": 3, "like": 470854, "dislike": 0, "vt": 0, "vv": 6589277}, "dynamic": "", "cid": 1318183732, "dimension": {"width": 1920, "height": 1080, "rotate": 0}, "short_link_v2": "https://b23.tv/BV1Tg4y1R7Sg", "first_frame": "http://i0.hdslb.com/bfs/storyff/n231101a22fo9ar90tb1322u0uklwq7v_firsti.jpg", "pub_location": "浙江", "cover43": "", "bvid": "BV1Tg4y1R7Sg", "season_type": 0, "is_ogv": false, "ogv_info": null, "enable_vt": 0, "ai_rcmd": null, "rcmd_reason": "用自己婚礼整活有多感动？快拿走我的祝福！"}, {"aid": 235186379, "videos": 1, "tid": 220, "tname": "动物二创", "copyright": 1, "pic": "http://i2.hdslb.com/bfs/archive/8578e320df38c915b7c1fc6826da7556befac9f1.jpg", "title": "当寄生虫感染上了寄生虫，谁能胜出？", "pubdate": 1698503847, "ctime": 1698503847, "desc": "", "state": 0, "duration": 601, "rights": {"bp": 0, "elec": 0, "download": 0, "movie": 0, "pay": 0, "hd5": 0, "no_reprint": 1, "autoplay": 1, "ugc_pay": 0, "is_cooperation": 0, "ugc_pay_preview": 0, "no_background": 0, "arc_pay": 0, "pay_free_watch": 0}, "owner": {"mid": 3493111665789758, "name": "纪录频道Nature", "face": "https://i2.hdslb.com/bfs/face/4dfe2aa8416e0216cda1b35c5e931111766d636d.jpg"}, "stat": {"aid": 235186379, "view": 12234759, "danmaku": 33920, "reply": 11193, "favorite": 214027, "coin": 116103, "share": 87434, "now_rank": 0, "his_rank": 4, "like": 596384, "dislike": 0, "vt": 0, "vv": 12234759}, "dynamic": "", "cid": 1314191555, "dimension": {"width": 1920, "height": 1080, "rotate": 0}, "short_link_v2": "https://b23.tv/BV1Ve41197Pq", "first_frame": "http://i2.hdslb.com/bfs/storyff/n231028sawfeymul5htru12vfj1b3pgo_firsti.jpg", "pub_location": "河南", "cover43": "", "bvid": "BV1Ve41197Pq", "season_type": 0, "is_ogv": false, "ogv_info": null, "enable_vt": 0, "ai_rcmd": null, "rcmd_reason": "神奇的大自然运行机制"}, {"aid": 280129629, "videos": 1, "tid": 21, "tname": "日常", "copyright": 1, "pic": "http://i0.hdslb.com/bfs/archive/66b82921ae213a86752e02b892ff4df7c9897ab6.jpg", "title": "【毕导】13年过去了，我终于毕业啦！", "pubdate": 1698462521, "ctime": 1698462521, "desc": "最近这两年半经常被大家催更，都给我催怕了！其实更新慢的原因也很简单，就是2020年12月我回去读博了，搞科研确实没时间更视频！不过今年7月，我终于博士毕业啦！今天就在这和大家聊聊天，分享一下这两年半的搞笑日常", "state": 0, "duration": 1219, "mission_id": 4005828, "rights": {"bp": 0, "elec": 0, "download": 0, "movie": 0, "pay": 0, "hd5": 1, "no_reprint": 1, "autoplay": 1, "ugc_pay": 0, "is_cooperation": 0, "ugc_pay_preview": 0, "no_background": 0, "arc_pay": 0, "pay_free_watch": 0}, "owner": {"mid": 254463269, "name": "毕导", "face": "https://i2.hdslb.com/bfs/face/a59d6b2dff6faa47bc07877b76f3194c598f5649.jpg"}, "stat": {"aid": 280129629, "view": 4696238, "danmaku": 18669, "reply": 6998, "favorite": 82964, "coin": 248827, "share": 48177, "now_rank": 0, "his_rank": 2, "like": 472296, "dislike": 0, "vt": 0, "vv": 4696238}, "dynamic": "我终于毕业了！！！（7月份毕的业，10月份才发视频庆祝，虽然很离谱，但在毕导这，倒也很正常。）", "cid": 1313429825, "dimension": {"width": 3840, "height": 2160, "rotate": 0}, "short_link_v2": "https://b23.tv/BV19c411o7os", "first_frame": "http://i2.hdslb.com/bfs/storyff/n231028sa580155cbk8m2drsjfbxegxm_firsti.jpg", "pub_location": "北京", "cover43": "", "bvid": "BV19c411o7os", "season_type": 0, "is_ogv": false, "ogv_info": null, "enable_vt": 0, "ai_rcmd": null, "rcmd_reason": "关于毕导在清华呆了13年这件事"}, {"aid": 535172114, "videos": 1, "tid": 228, "tname": "人文历史", "copyright": 1, "pic": "http://i1.hdslb.com/bfs/archive/7ce0facf77b5767de62e4f3caf65e30f959e5d9a.jpg", "title": "印度公主如何成为英国特工？【硬核狠人60】", "pubdate": 1698656400, "ctime": 1698401744, "desc": "本篇为硬核狠人之努尔。\n\n参考资料：\n巴苏·什拉巴尼2006年出版《间谍公主：努尔·伊纳亚特·汗的一生》\n拜伦·埃斯科特2012年出版《SOE：F部门：英国在法国的秘密女特工》\n莎拉·赫尔姆2007年出版《秘密生活：薇拉·阿特金斯和二战失踪特工》\n莫里斯·巴克拉马斯1988年出版《他们孤军奋战：战时法国SOE特工的真实故事》\n里克·斯特莱德2017年出版《孤独的勇气：SOE女英雄为解放纳粹占领的法国而战的真实故事》\n马库斯·宾尼2002年出版《为危险而生的女性：二战中SOE的女特工》", "state": 0, "duration": 1767, "rights": {"bp": 0, "elec": 0, "download": 0, "movie": 0, "pay": 0, "hd5": 1, "no_reprint": 1, "autoplay": 1, "ugc_pay": 0, "is_cooperation": 0, "ugc_pay_preview": 0, "no_background": 0, "arc_pay": 0, "pay_free_watch": 0}, "owner": {"mid": 23947287, "name": "小约翰可汗", "face": "https://i0.hdslb.com/bfs/face/347fec57de8b40e2818c0ca94253ac9ee5245a40.jpg"}, "stat": {"aid": 535172114, "view": 4321507, "danmaku": 24963, "reply": 7277, "favorite": 42572, "coin": 130513, "share": 8508, "now_rank": 0, "his_rank": 4, "like": 268718, "dislike": 0, "vt": 0, "vv": 4321507}, "dynamic": "本篇为硬核狠人之努尔。", "cid": 1312844116, "dimension": {"width": 1920, "height": 1080, "rotate": 0}, "season_id": 3491, "short_link_v2": "https://b23.tv/BV16M411X7A6", "first_frame": "http://i2.hdslb.com/bfs/storyff/n231027sa229ussf2wgtsr1slszwe8k2_firsti.jpg", "pub_location": "江苏", "cover43": "", "bvid": "BV16M411X7A6", "season_type": 0, "is_ogv": false, "ogv_info": null, "enable_vt": 0, "ai_rcmd": null, "rcmd_reason": "幸运又努力的女战士"}, {"aid": 875239831, "videos": 1, "tid": 17, "tname": "单机游戏", "copyright": 1, "pic": "http://i0.hdslb.com/bfs/archive/c5527ea8ab68c6dbdef569ed5be05fd6428c083a.jpg", "title": "史上最打动人心的游戏，玩过的人都致郁了！", "pubdate": 1698380992, "ctime": 1698380992, "desc": "抽象、魔幻现实、诡异、童趣、诗意，这些词用来形容《艾迪芬奇的记忆》这款游戏实在是太合适了！\n此游戏的风格绝对称得上独特，希望大家喜欢！\n求求个三连啦！orz 磕头！", "state": 0, "duration": 1209, "mission_id": 4005197, "rights": {"bp": 0, "elec": 0, "download": 0, "movie": 0, "pay": 0, "hd5": 0, "no_reprint": 1, "autoplay": 1, "ugc_pay": 0, "is_cooperation": 0, "ugc_pay_preview": 0, "no_background": 0, "arc_pay": 0, "pay_free_watch": 0}, "owner": {"mid": 36789537, "name": "明月沧澜", "face": "https://i0.hdslb.com/bfs/face/8e68e7952594d485a322ec6ae8c6a33683dc59cf.jpg"}, "stat": {"aid": 875239831, "view": 3461851, "danmaku": 3978, "reply": 1614, "favorite": 79659, "coin": 25475, "share": 8523, "now_rank": 0, "his_rank": 9, "like": 204806, "dislike": 0, "vt": 0, "vv": 3461851}, "dynamic": "", "cid": 1312340170, "dimension": {"width": 1920, "height": 1080, "rotate": 0}, "season_id": 147391, "short_link_v2": "https://b23.tv/BV1zN4y1k7Z1", "first_frame": "http://i1.hdslb.com/bfs/storyff/n231027sa2j1557xn7x62r2eqsydn1e4_firsti.jpg", "pub_location": "湖北", "cover43": "", "bvid": "BV1zN4y1k7Z1", "season_type": 0, "is_ogv": false, "ogv_info": null, "enable_vt": 0, "ai_rcmd": null, "rcmd_reason": "超小众的魔幻现实风格游戏"}, {"aid": 492667755, "videos": 1, "tid": 85, "tname": "小剧场", "copyright": 1, "pic": "http://i1.hdslb.com/bfs/archive/93f78b240f458a3cb8579f07b52f57b9ec247df2.jpg", "title": "创死心里每一只小鹿", "pubdate": 1698476220, "ctime": 1698476221, "desc": "-", "state": 0, "duration": 130, "mission_id": 4005420, "rights": {"bp": 0, "elec": 0, "download": 0, "movie": 0, "pay": 0, "hd5": 0, "no_reprint": 1, "autoplay": 1, "ugc_pay": 0, "is_cooperation": 0, "ugc_pay_preview": 0, "no_background": 0, "arc_pay": 0, "pay_free_watch": 0}, "owner": {"mid": 34009507, "name": "-显眼宝-", "face": "https://i1.hdslb.com/bfs/face/13b9f8b60804357d903cbfb38f69dd837a32f941.jpg"}, "stat": {"aid": 492667755, "view": 6264530, "danmaku": 4251, "reply": 2700, "favorite": 33106, "coin": 28432, "share": 13493, "now_rank": 0, "his_rank": 7, "like": 581012, "dislike": 0, "vt": 0, "vv": 6264530}, "dynamic": "", "cid": 1313683301, "dimension": {"width": 1080, "height": 1920, "rotate": 0}, "short_link_v2": "https://b23.tv/BV1oN411W76d", "up_from_v2": 35, "first_frame": "http://i0.hdslb.com/bfs/storyff/n231028bd53kmzrgne47f1kmp5wf6h02_firsti.jpg", "pub_location": "浙江", "cover43": "", "bvid": "BV1oN411W76d", "season_type": 0, "is_ogv": false, "ogv_info": null, "enable_vt": 0, "ai_rcmd": null, "rcmd_reason": "居然该死的有点甜"}, {"aid": 917642333, "videos": 1, "tid": 95, "tname": "数码", "copyright": 1, "pic": "http://i0.hdslb.com/bfs/archive/7128b11926e000e11f86600da720f726ccaf7131.jpg", "title": "「小白」关于小米 14/14 Pro 都在这了！", "pubdate": 1698364800, "ctime": 1698335082, "desc": "关注微信公众号：小白测评 每晚发车不见不散", "state": 0, "duration": 1427, "rights": {"bp": 0, "elec": 0, "download": 0, "movie": 0, "pay": 0, "hd5": 0, "no_reprint": 1, "autoplay": 1, "ugc_pay": 0, "is_cooperation": 0, "ugc_pay_preview": 0, "no_background": 0, "arc_pay": 0, "pay_free_watch": 0}, "owner": {"mid": 8969156, "name": "小白测评", "face": "https://i2.hdslb.com/bfs/face/09dd0d38633d567179784ac9a0d95ac1187ea71d.jpg"}, "stat": {"aid": 917642333, "view": 3418573, "danmaku": 19656, "reply": 10702, "favorite": 20357, "coin": 56218, "share": 20153, "now_rank": 0, "his_rank": 29, "like": 121826, "dislike": 0, "vt": 0, "vv": 3418573}, "dynamic": "「小白」关于小米 14/14 Pro 都在这了！\n上期详细跟大家聊了8Gen3的性能和能效，还有小米 14的游戏表现，本期补齐14和14 Pro的所有数据，还有影像和软件环节，这一代的影像水平如何？澎湃OS相比于MIUI有哪些改进呢？本期全告诉你，记得点赞~感谢啦！", "cid": 1312123171, "dimension": {"width": 4096, "height": 1890, "rotate": 0}, "season_id": 154, "short_link_v2": "https://b23.tv/BV1nu4y1Y7XZ", "first_frame": "http://i0.hdslb.com/bfs/storyff/n231026sa2qtd0ne2npz9w2pnovkxn59_firsti.jpg", "pub_location": "湖北", "cover43": "", "bvid": "BV1nu4y1Y7XZ", "season_type": 0, "is_ogv": false, "ogv_info": null, "enable_vt": 0, "ai_rcmd": null, "rcmd_reason": "小米新机实机测评"}, {"aid": 962419476, "videos": 1, "tid": 250, "tname": "出行", "copyright": 1, "pic": "http://i2.hdslb.com/bfs/archive/bd6ed0555706853f148c23ba22419c04c750697b.jpg", "title": "送盲人一只「电子导盲犬」，能代替真狗吗？！", "pubdate": 1697968867, "ctime": 1697965281, "desc": "这次真的很幸运能和2名优秀的up主一起拍摄。希望未来有一天电子导盲犬真的可以问世，帮助更多人。", "state": 0, "duration": 560, "rights": {"bp": 0, "elec": 0, "download": 0, "movie": 0, "pay": 0, "hd5": 1, "no_reprint": 1, "autoplay": 1, "ugc_pay": 0, "is_cooperation": 1, "ugc_pay_preview": 0, "no_background": 0, "arc_pay": 0, "pay_free_watch": 0}, "owner": {"mid": 361556391, "name": "庄子HD", "face": "https://i0.hdslb.com/bfs/face/c8d695112d25819a0ec162c5753c7e0e97f6cd9a.jpg"}, "stat": {"aid": 962419476, "view": 4160880, "danmaku": 2180, "reply": 2247, "favorite": 17625, "coin": 11472, "share": 1473, "now_rank": 0, "his_rank": 0, "like": 67281, "dislike": 0, "vt": 0, "vv": 4160880}, "dynamic": "hi 好久不见，\n这期视频是我们邀请了一位盲人up主体验电子导盲犬。\n过程中发生了有趣的事情，\n希望大家喜欢！", "cid": 1307584837, "dimension": {"width": 3840, "height": 2160, "rotate": 0}, "season_id": 2552, "short_link_v2": "https://b23.tv/BV1AH4y197m6", "first_frame": "http://i2.hdslb.com/bfs/storyff/n231022sa16l4zxhgfr68k2z42k8k3d9_firsti.jpg", "pub_location": "陕西", "cover43": "", "bvid": "BV1AH4y197m6", "season_type": 0, "is_ogv": false, "ogv_info": null, "enable_vt": 0, "ai_rcmd": null, "rcmd_reason": "电子导盲犬效果如何？"}, {"aid": 492649539, "videos": 1, "tid": 76, "tname": "美食制作", "copyright": 1, "pic": "http://i0.hdslb.com/bfs/archive/6ccd0c14c9c17bb7f6b700117f3368e1984a3433.jpg", "title": "如何在家制造可食用餐具", "pubdate": 1698483600, "ctime": 1698463854, "desc": "本次展示了一种可食用餐具的制作方法\n非常，非常不好意思啊 ，各位朋友，这次拖更了这么久，我之后尽量保证月更\n然后，非常非常感谢各位朋友，在我遇到困难无助时给了我很多建议、思路和帮助，真心谢谢各位!!!", "state": 0, "duration": 479, "rights": {"bp": 0, "elec": 0, "download": 0, "movie": 0, "pay": 0, "hd5": 1, "no_reprint": 1, "autoplay": 1, "ugc_pay": 0, "is_cooperation": 0, "ugc_pay_preview": 0, "no_background": 0, "arc_pay": 0, "pay_free_watch": 0}, "owner": {"mid": 349717298, "name": "嘤武罗", "face": "https://i2.hdslb.com/bfs/face/7b571c2dce8cc8476ef4ad6fdc46a8fa8ae48203.jpg"}, "stat": {"aid": 492649539, "view": 8959017, "danmaku": 10397, "reply": 2302, "favorite": 102872, "coin": 138201, "share": 4234, "now_rank": 0, "his_rank": 7, "like": 591637, "dislike": 0, "vt": 0, "vv": 8959017}, "dynamic": "", "cid": 1313512552, "dimension": {"width": 1920, "height": 1080, "rotate": 0}, "short_link_v2": "https://b23.tv/BV1SN411W74G", "first_frame": "http://i1.hdslb.com/bfs/storyff/n231028a22g9itdez0ugyg1i9rk2ks45_firsti.jpg", "pub_location": "福建", "cover43": "", "bvid": "BV1SN411W74G", "season_type": 0, "is_ogv": false, "ogv_info": null, "enable_vt": 0, "ai_rcmd": null, "rcmd_reason": "可食用但是不溶于水的汤勺有多神奇？"}, {"aid": 280143833, "videos": 1, "tid": 21, "tname": "日常", "copyright": 1, "pic": "http://i1.hdslb.com/bfs/archive/cdb8c094fbec3838746a9f7e4b8646174ebbf414.jpg", "title": "致1000年后，这是1215个人留下的信息。", "pubdate": 1698570000, "ctime": 1698517605, "desc": "这次征集我们一共收到了1215份投稿，每个人都将自己当下最珍贵的时刻以影像的方式记录下来，希望能传达给1000年的人们。感谢所有参与投稿的小伙伴们！\n如果你喜欢这期视频，也请多多支持我们，或者分享给其他朋友一起看看！\n*稿件入选的朋友（见片尾名单），我们将会在20个工作日内以短信的方式联系发放奖品。", "state": 0, "duration": 503, "mission_id": 1703831, "rights": {"bp": 0, "elec": 0, "download": 0, "movie": 0, "pay": 0, "hd5": 1, "no_reprint": 1, "autoplay": 1, "ugc_pay": 0, "is_cooperation": 0, "ugc_pay_preview": 0, "no_background": 0, "arc_pay": 0, "pay_free_watch": 0}, "owner": {"mid": 946974, "name": "影视飓风", "face": "https://i0.hdslb.com/bfs/face/c1733474892caa45952b2c09a89323157df7129a.jpg"}, "stat": {"aid": 280143833, "view": 2174502, "danmaku": 6412, "reply": 3787, "favorite": 61841, "coin": 97144, "share": 15667, "now_rank": 0, "his_rank": 12, "like": 221127, "dislike": 0, "vt": 0, "vv": 2174502}, "dynamic": "感谢所有参与本次征集的朋友！", "cid": 1324160101, "dimension": {"width": 3840, "height": 2160, "rotate": 0}, "season_id": 1994219, "short_link_v2": "https://b23.tv/BV1Mc411Z7VY", "first_frame": "http://i1.hdslb.com/bfs/storyff/n231107sa1r4kk97bvf3xi2du2l7vk1e_firsti.jpg", "pub_location": "浙江", "cover43": "", "bvid": "BV1Mc411Z7VY", "season_type": 0, "is_ogv": false, "ogv_info": null, "enable_vt": 0, "ai_rcmd": null, "rcmd_reason": "千年以后，谁还记得我们"}, {"aid": 962522965, "videos": 1, "tid": 172, "tname": "手机游戏", "copyright": 1, "pic": "http://i2.hdslb.com/bfs/archive/2843c0589cd431932a8e8b242f24727a90a609b1.jpg", "title": "《白荆回廊》终极测试 | Binary Star全新单曲「偶像自白书」正式发布", "pubdate": 1698804000, "ctime": 1698072250, "desc": "《白荆回廊》终极测试 | Binary Star全新单曲「偶像自白书」正式发布\n\n「删除数据，删除被迫参与流行，\n做个怪胎，也只做我自己。」\n\n演唱：Binary Star（司危 / 芙蕖）\n作词：恨醉\n作曲/编曲：林子LIN\n和声编写/混音/母带：声罗万象工作室\n出品：神奇漂浮 LVT Entertainment", "state": 0, "duration": 130, "rights": {"bp": 0, "elec": 0, "download": 0, "movie": 0, "pay": 0, "hd5": 0, "no_reprint": 1, "autoplay": 1, "ugc_pay": 0, "is_cooperation": 0, "ugc_pay_preview": 0, "no_background": 0, "arc_pay": 0, "pay_free_watch": 0}, "owner": {"mid": 1881796598, "name": "白荆回廊", "face": "https://i2.hdslb.com/bfs/face/b1343f27ad2e26a867a0f158a33e372c9bf4556a.jpg"}, "stat": {"aid": 962522965, "view": 7503586, "danmaku": 2264, "reply": 2591, "favorite": 49685, "coin": 57065, "share": 4130, "now_rank": 0, "his_rank": 4, "like": 115671, "dislike": 0, "vt": 0, "vv": 7503586}, "dynamic": "", "cid": 1317705986, "dimension": {"width": 2560, "height": 1440, "rotate": 0}, "short_link_v2": "https://b23.tv/BV1eH4y197Rs", "first_frame": "http://i2.hdslb.com/bfs/storyff/n231101a2865q3uif9hh23fvu7f4g2sl_firsti.jpg", "pub_location": "上海", "cover43": "", "bvid": "BV1eH4y197Rs", "season_type": 0, "is_ogv": false, "ogv_info": null, "enable_vt": 0, "ai_rcmd": null, "rcmd_reason": "「删除数据，删除被迫参与流行， 做个怪胎，也只做我自己。」"}, {"aid": 662650417, "videos": 1, "tid": 17, "tname": "单机游戏", "copyright": 1, "pic": "http://i2.hdslb.com/bfs/archive/e316ca0cf5c69945438671b097546a8bbd64656b.jpg", "title": "【爆肝】挑战在一个区块里生存100天，直接挖空！", "pubdate": 1698398068, "ctime": 1698398068, "desc": "久违的生存系列来啦！这个系列应该两期完结，全程基本直播进行。\n想看续集的话，就三连支持这期视频叭！这对于我帮助很大。", "state": 0, "duration": 715, "mission_id": 4005870, "rights": {"bp": 0, "elec": 0, "download": 0, "movie": 0, "pay": 0, "hd5": 0, "no_reprint": 1, "autoplay": 1, "ugc_pay": 0, "is_cooperation": 0, "ugc_pay_preview": 0, "no_background": 0, "arc_pay": 0, "pay_free_watch": 0}, "owner": {"mid": 390527713, "name": "史蒂猪StevenPig", "face": "https://i1.hdslb.com/bfs/face/c2af6c3fbd22088e3e0decd97ce5ea504d4996e2.jpg"}, "stat": {"aid": 662650417, "view": 11092556, "danmaku": 6374, "reply": 1540, "favorite": 169034, "coin": 147609, "share": 6579, "now_rank": 0, "his_rank": 11, "like": 371679, "dislike": 0, "vt": 0, "vv": 11092556}, "dynamic": "【爆肝】挑战在一个区块里生存100天，直接先挖空！", "cid": 1312767421, "dimension": {"width": 1920, "height": 1080, "rotate": 0}, "season_id": 1903949, "short_link_v2": "https://b23.tv/BV1ch4y1q7Zd", "first_frame": "http://i1.hdslb.com/bfs/storyff/n231027sa4sdtcjhnk0ie2fmsiy812xr_firsti.jpg", "pub_location": "贵州", "cover43": "", "bvid": "BV1ch4y1q7Zd", "season_type": 0, "is_ogv": false, "ogv_info": null, "enable_vt": 0, "ai_rcmd": null, "rcmd_reason": "省流：被挖空了"}, {"aid": 450347862, "videos": 1, "tid": 171, "tname": "电子竞技", "copyright": 1, "pic": "http://i2.hdslb.com/bfs/archive/3f9f5b4d05100e980f403cfd5a14691c1077f3f5.jpg", "title": "【2023共创之夜】完整版回放：欢迎来到王者荣耀", "pubdate": 1698570580, "ctime": 1698570580, "desc": "欢迎来到王者荣耀，欢迎来到2023共创之夜！王者IP内容重磅发布、高燃舞台精彩纷呈，又是一年相伴，小王与每一位不可或缺的你约定未来携手前行！", "state": 0, "duration": 12654, "rights": {"bp": 0, "elec": 0, "download": 0, "movie": 0, "pay": 0, "hd5": 0, "no_reprint": 1, "autoplay": 1, "ugc_pay": 0, "is_cooperation": 0, "ugc_pay_preview": 0, "no_background": 0, "arc_pay": 0, "pay_free_watch": 0}, "owner": {"mid": 57863910, "name": "王者荣耀", "face": "https://i0.hdslb.com/bfs/face/b98606398da2891c4089cf630c28a365e062fee8.jpg"}, "stat": {"aid": 450347862, "view": 10137042, "danmaku": 19873, "reply": 2917, "favorite": 40128, "coin": 58055, "share": 8517, "now_rank": 0, "his_rank": 2, "like": 212483, "dislike": 0, "vt": 0, "vv": 10137042}, "dynamic": "欢迎来到王者荣耀，欢迎来到2023共创之夜！王者IP内容重磅发布、高燃舞台精彩纷呈，又是一年相伴，小王与每一位不可或缺的你约定未来携手前行！", "cid": 1314806083, "dimension": {"width": 1920, "height": 1080, "rotate": 0}, "season_id": 1832687, "short_link_v2": "https://b23.tv/BV1Mj411v7Vy", "first_frame": "http://i1.hdslb.com/bfs/storyff/n231029sa1j4niy3dw6up7iseg0s72l3_firsti.jpg", "pub_location": "四川", "cover43": "", "bvid": "BV1Mj411v7Vy", "season_type": 0, "is_ogv": false, "ogv_info": null, "enable_vt": 0, "ai_rcmd": null, "rcmd_reason": "八周年生日快乐！"}, {"aid": 962778167, "videos": 1, "tid": 138, "tname": "搞笑", "copyright": 1, "pic": "http://i2.hdslb.com/bfs/archive/31aab8b5d5022c7cd6128aa99c8712ea07b54a04.jpg", "title": "各地人眼中的正宗美食", "pubdate": 1698750000, "ctime": 1698740365, "desc": "没想到这些都是盗版的！", "state": 0, "duration": 442, "mission_id": 4006050, "rights": {"bp": 0, "elec": 0, "download": 0, "movie": 0, "pay": 0, "hd5": 0, "no_reprint": 1, "autoplay": 1, "ugc_pay": 0, "is_cooperation": 0, "ugc_pay_preview": 0, "no_background": 0, "arc_pay": 0, "pay_free_watch": 0}, "owner": {"mid": 95515699, "name": "粤知一二", "face": "https://i1.hdslb.com/bfs/face/45526a0992aa6cb190863f49be6ac2f49f9bd8d9.jpg"}, "stat": {"aid": 962778167, "view": 6369301, "danmaku": 7769, "reply": 6023, "favorite": 37646, "coin": 10723, "share": 4695, "now_rank": 0, "his_rank": 4, "like": 379965, "dislike": 0, "vt": 0, "vv": 6369301}, "dynamic": "没想到这些都是盗版的！#粤知一二##郭嘉峰##栋笃笑#", "cid": 1316969547, "dimension": {"width": 1080, "height": 1920, "rotate": 0}, "short_link_v2": "https://b23.tv/BV1tH4y1r71Z", "first_frame": "http://i1.hdslb.com/bfs/storyff/n231031sa5qr5b8kfqlfq33taq3mp55f_firsti.jpg", "pub_location": "广东", "cover43": "", "bvid": "BV1tH4y1r71Z", "season_type": 0, "is_ogv": false, "ogv_info": null, "enable_vt": 0, "ai_rcmd": null, "rcmd_reason": "南北差异真的很好玩"}, {"aid": 790267308, "videos": 1, "tid": 85, "tname": "小剧场", "copyright": 1, "pic": "http://i1.hdslb.com/bfs/archive/ed884d596d56c7653c14ea95246957fef95ba3d4.jpg", "title": "两个人的恋爱其实是两个寝室的努力！", "pubdate": 1698807600, "ctime": 1698782327, "desc": "", "state": 0, "duration": 107, "mission_id": 4005420, "rights": {"bp": 0, "elec": 0, "download": 0, "movie": 0, "pay": 0, "hd5": 0, "no_reprint": 1, "autoplay": 1, "ugc_pay": 0, "is_cooperation": 0, "ugc_pay_preview": 0, "no_background": 0, "arc_pay": 0, "pay_free_watch": 0}, "owner": {"mid": 3493271504423174, "name": "我是刘大悦le", "face": "https://i2.hdslb.com/bfs/face/2c67403fdf3809889f7da2f7133ea7f42218efec.jpg"}, "stat": {"aid": 790267308, "view": 4543899, "danmaku": 747, "reply": 1830, "favorite": 26726, "coin": 3199, "share": 7201, "now_rank": 0, "his_rank": 8, "like": 325455, "dislike": 0, "vt": 0, "vv": 4543899}, "dynamic": "", "cid": 1317578840, "dimension": {"width": 1080, "height": 1920, "rotate": 0}, "short_link_v2": "https://b23.tv/BV17y4y1A7bX", "first_frame": "http://i0.hdslb.com/bfs/storyff/n231101sa25n4vodb0rt7c2u8kb7ein2_firsti.jpg", "pub_location": "北京", "cover43": "", "bvid": "BV17y4y1A7bX", "season_type": 0, "is_ogv": false, "ogv_info": null, "enable_vt": 0, "ai_rcmd": null, "rcmd_reason": "两个”军事团队“促成一场恋爱"}, {"aid": 875276694, "videos": 1, "tid": 251, "tname": "三农", "copyright": 1, "pic": "http://i2.hdslb.com/bfs/archive/d95ad11ade45f587551338f9a285abf948700ae8.jpg", "title": "“如何征服全村的狗子”", "pubdate": 1698660000, "ctime": 1698653510, "desc": "-", "state": 0, "duration": 222, "mission_id": 1703934, "rights": {"bp": 0, "elec": 0, "download": 0, "movie": 0, "pay": 0, "hd5": 0, "no_reprint": 1, "autoplay": 1, "ugc_pay": 0, "is_cooperation": 0, "ugc_pay_preview": 0, "no_background": 0, "arc_pay": 0, "pay_free_watch": 0}, "owner": {"mid": 1457645949, "name": "吴木良", "face": "https://i0.hdslb.com/bfs/face/7b79ddeee76011f804e10cecc99ee5873dbebaeb.jpg"}, "stat": {"aid": 875276694, "view": 5923214, "danmaku": 4867, "reply": 2243, "favorite": 140394, "coin": 85622, "share": 10297, "now_rank": 0, "his_rank": 18, "like": 341955, "dislike": 0, "vt": 0, "vv": 5923214}, "dynamic": "", "cid": 1315893132, "dimension": {"width": 1920, "height": 1080, "rotate": 0}, "short_link_v2": "https://b23.tv/BV1DN4y1k7dH", "up_from_v2": 36, "first_frame": "http://i2.hdslb.com/bfs/storyff/n231030sa1c5tv6klxr7ki1ycc8evyrf_firsti.jpg", "pub_location": "福建", "cover43": "", "bvid": "BV1DN4y1k7dH", "season_type": 0, "is_ogv": false, "ogv_info": null, "enable_vt": 0, "ai_rcmd": null, "rcmd_reason": "村里的小土狗如何被征服？"}, {"aid": 790177703, "videos": 1, "tid": 65, "tname": "网络游戏", "copyright": 1, "pic": "http://i0.hdslb.com/bfs/archive/3b5577dbfd0fcf6fa2177e6e08c44caa7030e0b6.jpg", "title": "《王者荣耀世界》6分钟实机演示发布-「为战斗加点恶作剧」", "pubdate": 1698498600, "ctime": 1698467403, "desc": "容我为你展示极致的机关之美，\n接下来的演出，你也要起舞，\n接下来的冒险，跟随手环的指引，\n探寻世界的璀璨与奇迹。", "state": 0, "duration": 404, "rights": {"bp": 0, "elec": 0, "download": 0, "movie": 0, "pay": 0, "hd5": 0, "no_reprint": 1, "autoplay": 1, "ugc_pay": 0, "is_cooperation": 0, "ugc_pay_preview": 0, "no_background": 0, "arc_pay": 0, "pay_free_watch": 0}, "owner": {"mid": 57435565, "name": "王者荣耀世界", "face": "https://i1.hdslb.com/bfs/face/71be95dd5a3eee56a5fe3038d30d893b07c86979.jpg"}, "stat": {"aid": 790177703, "view": 3510762, "danmaku": 21207, "reply": 27262, "favorite": 10677, "coin": 8652, "share": 54376, "now_rank": 0, "his_rank": 33, "like": 120936, "dislike": 0, "vt": 0, "vv": 3510762}, "dynamic": "", "cid": 1313471467, "dimension": {"width": 3840, "height": 2160, "rotate": 0}, "short_link_v2": "https://b23.tv/BV1Sy4y1w7QM", "first_frame": "http://i0.hdslb.com/bfs/storyff/n231028sa26v5py62dcdrvv1vmvjohbg_firsti.jpg", "pub_location": "四川", "cover43": "", "bvid": "BV1Sy4y1w7QM", "season_type": 0, "is_ogv": false, "ogv_info": null, "enable_vt": 0, "ai_rcmd": null, "rcmd_reason": "好炫酷的大世界！"}, {"aid": 235294570, "videos": 1, "tid": 212, "tname": "美食侦探", "copyright": 1, "pic": "http://i0.hdslb.com/bfs/archive/f8be0a9965eed1f8f26bfc66961ca08a206848eb.jpg", "title": "100块挑战东北早市，看能不能把仨战士吃饱", "pubdate": 1698809400, "ctime": 1698749274, "desc": "-", "state": 0, "duration": 393, "mission_id": 1699265, "rights": {"bp": 0, "elec": 0, "download": 0, "movie": 0, "pay": 0, "hd5": 0, "no_reprint": 1, "autoplay": 1, "ugc_pay": 0, "is_cooperation": 0, "ugc_pay_preview": 0, "no_background": 0, "arc_pay": 0, "pay_free_watch": 0}, "owner": {"mid": 1618410357, "name": "吃不饱仨战士", "face": "https://i0.hdslb.com/bfs/face/3266bb1d6e99b29aa8cd218b83f0b1e45858771a.jpg"}, "stat": {"aid": 235294570, "view": 2770813, "danmaku": 3780, "reply": 3077, "favorite": 9019, "coin": 40774, "share": 7761, "now_rank": 0, "his_rank": 10, "like": 220613, "dislike": 0, "vt": 0, "vv": 2770813}, "dynamic": "", "cid": 1317148162, "dimension": {"width": 720, "height": 1280, "rotate": 0}, "short_link_v2": "https://b23.tv/BV1ve41197Zu", "up_from_v2": 9, "first_frame": "http://i1.hdslb.com/bfs/storyff/n231031sa27n6y3ayoa16622w3uzffvg_firsti.jpg", "pub_location": "浙江", "cover43": "", "bvid": "BV1ve41197Zu", "season_type": 0, "is_ogv": false, "ogv_info": null, "enable_vt": 0, "ai_rcmd": null, "rcmd_reason": "第一次看三战士面对食物无能为力"}, {"aid": 875192891, "videos": 1, "tid": 235, "tname": "篮球", "copyright": 1, "pic": "http://i0.hdslb.com/bfs/archive/0acd17ae3201c3e4e68aba9e7f99ce48166a0cb4.jpg", "title": "上课做梦打球，10秒内笑失声系列！！！", "pubdate": 1698453000, "ctime": 1698424790, "desc": "-", "state": 0, "duration": 83, "rights": {"bp": 0, "elec": 0, "download": 0, "movie": 0, "pay": 0, "hd5": 0, "no_reprint": 1, "autoplay": 1, "ugc_pay": 0, "is_cooperation": 0, "ugc_pay_preview": 0, "no_background": 0, "arc_pay": 0, "pay_free_watch": 0}, "owner": {"mid": 511575069, "name": "No-Solution篮球", "face": "https://i0.hdslb.com/bfs/face/17d87d4a7598db44df64cd5c1897750dc1c44e67.jpg"}, "stat": {"aid": 875192891, "view": 6362345, "danmaku": 2709, "reply": 2569, "favorite": 174073, "coin": 48174, "share": 51891, "now_rank": 0, "his_rank": 4, "like": 662048, "dislike": 0, "vt": 0, "vv": 6362345}, "dynamic": "", "cid": 1313242795, "dimension": {"width": 1080, "height": 1920, "rotate": 0}, "short_link_v2": "https://b23.tv/BV1jN4y1k7e5", "up_from_v2": 36, "first_frame": "http://i0.hdslb.com/bfs/storyff/n231028sa1p25io8ftyc4j2p2e989hnc_firsti.jpg", "pub_location": "贵州", "cover43": "", "bvid": "BV1jN4y1k7e5", "season_type": 0, "is_ogv": false, "ogv_info": null, "enable_vt": 0, "ai_rcmd": null, "rcmd_reason": "梦游了这是？"}, {"aid": 235209804, "videos": 1, "tid": 251, "tname": "三农", "copyright": 1, "pic": "http://i1.hdslb.com/bfs/archive/74623f41673870685bac0f371f88a651868c3c39.jpg", "title": "83岁老人，一人一车骑行全国，一天一百到两百公里，直接刷新了我的认知", "pubdate": 1698478254, "ctime": 1698478254, "desc": "", "state": 0, "duration": 97, "mission_id": 1699292, "rights": {"bp": 0, "elec": 0, "download": 0, "movie": 0, "pay": 0, "hd5": 0, "no_reprint": 1, "autoplay": 1, "ugc_pay": 0, "is_cooperation": 0, "ugc_pay_preview": 0, "no_background": 0, "arc_pay": 0, "pay_free_watch": 0}, "owner": {"mid": 3493123130919728, "name": "我是凡人繁星", "face": "https://i2.hdslb.com/bfs/face/dad0d1747a7f2a622ffca757d60685164656a4eb.jpg"}, "stat": {"aid": 235209804, "view": 1585506, "danmaku": 2085, "reply": 2869, "favorite": 18802, "coin": 12241, "share": 9993, "now_rank": 0, "his_rank": 0, "like": 177749, "dislike": 0, "vt": 0, "vv": 1585506}, "dynamic": "", "cid": 1313752205, "dimension": {"width": 1080, "height": 1920, "rotate": 0}, "short_link_v2": "https://b23.tv/BV1ne41197CJ", "first_frame": "http://i0.hdslb.com/bfs/storyff/n231028sa2cq5pr997dr8812urbqptmx_firsti.jpg", "pub_location": "甘肃", "cover43": "", "bvid": "BV1ne41197CJ", "season_type": 0, "is_ogv": false, "ogv_info": null, "enable_vt": 0, "ai_rcmd": null, "rcmd_reason": "83岁老人骑行之旅"}, {"aid": 705356325, "videos": 1, "tid": 85, "tname": "小剧场", "copyright": 1, "pic": "http://i2.hdslb.com/bfs/archive/d9d22d565e933e6d5d061c94feaebd60db1f2a59.jpg", "title": "当父母来到你的城市", "pubdate": 1698657157, "ctime": 1698657158, "desc": "", "state": 0, "duration": 108, "mission_id": 4005420, "rights": {"bp": 0, "elec": 0, "download": 0, "movie": 0, "pay": 0, "hd5": 0, "no_reprint": 1, "autoplay": 1, "ugc_pay": 0, "is_cooperation": 0, "ugc_pay_preview": 0, "no_background": 0, "arc_pay": 0, "pay_free_watch": 0}, "owner": {"mid": 1614789471, "name": "派小轩", "face": "https://i0.hdslb.com/bfs/face/452f239756a610ef39b377b32b2b140f9794b487.jpg"}, "stat": {"aid": 705356325, "view": 4615099, "danmaku": 748, "reply": 2118, "favorite": 10009, "coin": 9405, "share": 2618, "now_rank": 0, "his_rank": 22, "like": 334017, "dislike": 0, "vt": 0, "vv": 4615099}, "dynamic": "", "cid": 1315746866, "dimension": {"width": 1080, "height": 1920, "rotate": 0}, "short_link_v2": "https://b23.tv/BV1SQ4y1H7gQ", "first_frame": "http://i1.hdslb.com/bfs/storyff/n231030sa2tpjkvirqugpd2dpei6y243_firsti.jpg", "pub_location": "北京", "cover43": "", "bvid": "BV1SQ4y1H7gQ", "season_type": 0, "is_ogv": false, "ogv_info": null, "enable_vt": 0, "ai_rcmd": null, "rcmd_reason": "“我的眼泪从打开冰箱那儿收回来了”"}, {"aid": 917740008, "videos": 1, "tid": 207, "tname": "财经商业", "copyright": 1, "pic": "http://i0.hdslb.com/bfs/archive/ad174132f0592bc0a9d4239902f026b533688a22.jpg", "title": "【半佛】喜茶疯了，奶茶哭了", "pubdate": 1698390000, "ctime": 1698321308, "desc": "是时候来点真正的疯狂了。", "state": 0, "duration": 527, "mission_id": 1698492, "rights": {"bp": 0, "elec": 0, "download": 0, "movie": 0, "pay": 0, "hd5": 0, "no_reprint": 1, "autoplay": 1, "ugc_pay": 0, "is_cooperation": 0, "ugc_pay_preview": 0, "no_background": 0, "arc_pay": 0, "pay_free_watch": 0}, "owner": {"mid": 37663924, "name": "硬核的半佛仙人", "face": "https://i1.hdslb.com/bfs/face/aaf33dced1941af0946f37c62f4b48fcaba9c9a2.jpg"}, "stat": {"aid": 917740008, "view": 2310889, "danmaku": 2664, "reply": 3580, "favorite": 6701, "coin": 5988, "share": 5670, "now_rank": 0, "his_rank": 0, "like": 83410, "dislike": 0, "vt": 0, "vv": 2310889}, "dynamic": "来点真正的商战刺激。", "cid": 1311895359, "dimension": {"width": 1920, "height": 1080, "rotate": 0}, "short_link_v2": "https://b23.tv/BV1Qu4y1Y7t8", "first_frame": "http://i1.hdslb.com/bfs/storyff/n231026sa2rroky5z8peo31vdai2sy5u_firsti.jpg", "pub_location": "浙江", "cover43": "", "bvid": "BV1Qu4y1Y7t8", "season_type": 0, "is_ogv": false, "ogv_info": null, "enable_vt": 0, "ai_rcmd": null, "rcmd_reason": "奶茶届内卷到什么程度了？"}, {"aid": 832719161, "videos": 1, "tid": 21, "tname": "日常", "copyright": 1, "pic": "http://i0.hdslb.com/bfs/archive/8014b59c1257de3702102cf4367bf3e9bbc28d9a.jpg", "title": "因为生理羞耻，我被一群小学生嘲笑了….", "pubdate": 1698491685, "ctime": 1698491685, "desc": "其实上这次课之前，我担心孩子们对这节课没什么兴趣，但没想到大家都踊跃发言回答问题，很给我面子，后来也和他们成为了朋友，这是一群淳朴可爱的孩子。我觉得为什么一提到卫生巾会有学生发出嘲笑的声音，很大程度上还是因为对这个东西不了解。村里大多都是老人照顾孩子，父母外出打工，不会特别重视生理卫生的教育，这也是我为什么会上这节课的原因。希望大家给孩子们多一些宽容，一起帮助他们更好的成长", "state": 0, "duration": 369, "mission_id": 4005828, "rights": {"bp": 0, "elec": 0, "download": 0, "movie": 0, "pay": 0, "hd5": 1, "no_reprint": 1, "autoplay": 1, "ugc_pay": 0, "is_cooperation": 0, "ugc_pay_preview": 0, "no_background": 0, "arc_pay": 0, "pay_free_watch": 0}, "owner": {"mid": 11870568, "name": "拉宏桑", "face": "https://i0.hdslb.com/bfs/face/a630e4e7e06ec2ed50425cbb53bcf6e8ff885726.jpg"}, "stat": {"aid": 832719161, "view": 4461349, "danmaku": 7215, "reply": 7086, "favorite": 65183, "coin": 163617, "share": 11323, "now_rank": 0, "his_rank": 11, "like": 301053, "dislike": 0, "vt": 0, "vv": 4461349}, "dynamic": "", "cid": 1316844099, "dimension": {"width": 1920, "height": 1080, "rotate": 0}, "short_link_v2": "https://b23.tv/BV1Qg4y1d72Z", "first_frame": "http://i0.hdslb.com/bfs/storyff/n231031sa1sfl82bveh89l21zvxytfpi_firsti.jpg", "pub_location": "广东", "cover43": "", "bvid": "BV1Qg4y1d72Z", "season_type": 0, "is_ogv": false, "ogv_info": null, "enable_vt": 0, "ai_rcmd": null, "rcmd_reason": "拒绝月经羞耻"}, {"aid": 322834920, "videos": 1, "tid": 157, "tname": "美妆护肤", "copyright": 1, "pic": "http://i2.hdslb.com/bfs/archive/06f9898cc4dfb01391ca2f786d9024f6a050a777.jpg", "title": "粉墨设计师给我做衣服？！万元明星礼服随便穿", "pubdate": 1698667800, "ctime": 1698657954, "desc": "Black Pink的设计师居然要给我做衣服？！万元明星同款礼服随便试？", "state": 0, "duration": 486, "mission_id": 1703934, "rights": {"bp": 0, "elec": 0, "download": 0, "movie": 0, "pay": 0, "hd5": 0, "no_reprint": 1, "autoplay": 1, "ugc_pay": 0, "is_cooperation": 0, "ugc_pay_preview": 0, "no_background": 0, "arc_pay": 0, "pay_free_watch": 0}, "owner": {"mid": 15892313, "name": "知名相声演员BBBBB大王", "face": "https://i2.hdslb.com/bfs/face/e40bb6be0e7aa5d3f2838313bb47a59358481577.jpg"}, "stat": {"aid": 322834920, "view": 1733163, "danmaku": 2372, "reply": 732, "favorite": 5737, "coin": 4786, "share": 893, "now_rank": 0, "his_rank": 0, "like": 80755, "dislike": 0, "vt": 0, "vv": 1733163}, "dynamic": "Black Pink的设计师居然要给我做衣服？！万元明星同款礼服随便试？", "cid": 1315975972, "dimension": {"width": 1920, "height": 1080, "rotate": 0}, "short_link_v2": "https://b23.tv/BV1Rw411q77B", "first_frame": "http://i1.hdslb.com/bfs/storyff/n231030sa309qmf0um9tzk1ea2s4fiv2_firsti.jpg", "pub_location": "江苏", "cover43": "", "bvid": "BV1Rw411q77B", "season_type": 0, "is_ogv": false, "ogv_info": null, "enable_vt": 0, "ai_rcmd": null, "rcmd_reason": "女团cody给BB做造型"}, {"aid": 920241016, "videos": 1, "tid": 27, "tname": "综合", "copyright": 1, "pic": "http://i0.hdslb.com/bfs/archive/8ccd57c64aea388d478253ef76f5590d26d6b6ca.jpg", "title": "误入咒术片场无故加班的普通上班族", "pubdate": 1698466500, "ctime": 1698445816, "desc": "没有一刻为五条悟被封印感到悲伤，立刻赶往战场的是普通上班族", "state": 0, "duration": 134, "rights": {"bp": 0, "elec": 0, "download": 0, "movie": 0, "pay": 0, "hd5": 0, "no_reprint": 1, "autoplay": 1, "ugc_pay": 0, "is_cooperation": 0, "ugc_pay_preview": 0, "no_background": 0, "arc_pay": 0, "pay_free_watch": 0}, "owner": {"mid": 25011599, "name": "哦桑ohsan", "face": "https://i2.hdslb.com/bfs/face/4c7b295b877e04648f89113627fa94d62e7a472e.jpg"}, "stat": {"aid": 920241016, "view": 1917357, "danmaku": 851, "reply": 1146, "favorite": 26821, "coin": 10111, "share": 7745, "now_rank": 0, "his_rank": 0, "like": 127202, "dislike": 0, "vt": 0, "vv": 1917357}, "dynamic": "", "cid": 1313331177, "dimension": {"width": 1920, "height": 1080, "rotate": 0}, "short_link_v2": "https://b23.tv/BV1zu4y1E7oH", "first_frame": "http://i2.hdslb.com/bfs/storyff/n231028sap7goxpample63bprziutfw3_firsti.jpg", "pub_location": "云南", "cover43": "", "bvid": "BV1zu4y1E7oH", "season_type": 0, "is_ogv": false, "ogv_info": null, "enable_vt": 0, "ai_rcmd": null, "rcmd_reason": "没有一刻为五条悟被封印感到悲伤，立刻赶往战场的是普通上班族"}, {"aid": 875051690, "videos": 4, "tid": 172, "tname": "手机游戏", "copyright": 1, "pic": "http://i1.hdslb.com/bfs/archive/d01af8beaec17629447cae0193f5a106c0791c0e.jpg", "title": "《崩坏：星穹铁道》托帕&账账角色PV——「专家教学」", "pubdate": 1698292800, "ctime": 1698250453, "desc": "「托帕」\n定级：P45\n所属：星际和平公司>战略投资部>重大事务组>不良资产清算专家\n\n综合绩效评定 第8位\n\n中文CV：\n托帕——陆敏悦\n账账——陆敏悦\n叽米——刘北辰\n桑博——刘圣博\n黑塔——侯小菲\n艾丝妲——龟娘\n\n日文CV：\n托帕——南条爱乃\n账账——陆敏悦\n叽米——名村幸太朗\n桑博——平川大辅\n黑塔——山崎遥\n艾丝妲——赤崎千夏\n\n英文CV：\n托帕——Sam Slade\n账账——陆敏悦\n叽米——Bill Butts\n桑博——Roger Rose\n黑塔——PJ Mattson\n艾丝妲——Felec", "state": 0, "duration": 470, "rights": {"bp": 0, "elec": 0, "download": 0, "movie": 0, "pay": 0, "hd5": 1, "no_reprint": 1, "autoplay": 1, "ugc_pay": 0, "is_cooperation": 0, "ugc_pay_preview": 0, "no_background": 0, "arc_pay": 0, "pay_free_watch": 0}, "owner": {"mid": 1340190821, "name": "崩坏星穹铁道", "face": "https://i2.hdslb.com/bfs/face/a6419a5f230c500962c7954c907be74a7cbd61b5.jpg"}, "stat": {"aid": 875051690, "view": 4108319, "danmaku": 10288, "reply": 8512, "favorite": 51439, "coin": 71096, "share": 29302, "now_rank": 0, "his_rank": 3, "like": 255329, "dislike": 0, "vt": 0, "vv": 4108319}, "dynamic": "#崩坏星穹铁道# #冬梦激醒# #星穹铁道托帕#\n\n「托帕」\n定级：P45\n所属：星际和平公司>战略投资部>重大事务组>不良资产清算专家\n\n综合绩效评定 第8位", "cid": 1311169500, "dimension": {"width": 1920, "height": 1080, "rotate": 0}, "short_link_v2": "https://b23.tv/BV1kN4y1r7AL", "first_frame": "http://i0.hdslb.com/bfs/storyff/n231025saqe2s17oxo91b309b4db6tzc_firsti.jpg", "pub_location": "上海", "cover43": "", "bvid": "BV1kN4y1r7AL", "season_type": 0, "is_ogv": false, "ogv_info": null, "enable_vt": 0, "ai_rcmd": null, "rcmd_reason": "好高超的PV技术力！"}, {"aid": 450269860, "videos": 1, "tid": 21, "tname": "日常", "copyright": 1, "pic": "http://i0.hdslb.com/bfs/archive/68cc2209139c68aca238ca3588558948cc4f3b22.jpg", "title": "【vlog】骑着小破车去到内蒙古，找回重新开始的勇气", "pubdate": 1698660000, "ctime": 1698627920, "desc": "前路漫漫  道阻且长  行则将至  做则必成", "state": 0, "duration": 1910, "rights": {"bp": 0, "elec": 0, "download": 0, "movie": 0, "pay": 0, "hd5": 0, "no_reprint": 1, "autoplay": 1, "ugc_pay": 0, "is_cooperation": 0, "ugc_pay_preview": 0, "no_background": 0, "arc_pay": 0, "pay_free_watch": 0}, "owner": {"mid": 1850720242, "name": "小缸", "face": "https://i1.hdslb.com/bfs/face/b6d24f0e62af828835b471ada06f6a3b97549cbc.jpg"}, "stat": {"aid": 450269860, "view": 1324778, "danmaku": 29580, "reply": 8685, "favorite": 64007, "coin": 281719, "share": 18289, "now_rank": 0, "his_rank": 5, "like": 173423, "dislike": 0, "vt": 0, "vv": 1324778}, "dynamic": "何德何能，遇到万千分之一的你们", "cid": 1315494528, "dimension": {"width": 4680, "height": 2160, "rotate": 0}, "season_id": 1866853, "short_link_v2": "https://b23.tv/BV19j411e71L", "first_frame": "http://i1.hdslb.com/bfs/storyff/n231030sacsxkeq3fhu7iixwzct7acd2_firsti.jpg", "pub_location": "湖南", "cover43": "", "bvid": "BV19j411e71L", "season_type": 0, "is_ogv": false, "ogv_info": null, "enable_vt": 0, "ai_rcmd": null, "rcmd_reason": "祝我们都有从头再来的勇气"}, {"aid": 280496928, "videos": 1, "tid": 95, "tname": "数码", "copyright": 1, "pic": "http://i1.hdslb.com/bfs/archive/23312a9493d8fa51305f1359357b461ba6fecee9.jpg", "title": "星闪技术上手体验：万物互联的根基？", "pubdate": 1698918771, "ctime": 1698918771, "desc": "这次我们体验了新一代的通信技术——星闪。作为未来物联网互联的新标准，星闪到底是什么样的技术？相比蓝牙优势在哪里？星闪设备实测表现如何呢？今天的视频给你答案……", "state": 0, "duration": 576, "mission_id": 1703831, "rights": {"bp": 0, "elec": 0, "download": 0, "movie": 0, "pay": 0, "hd5": 0, "no_reprint": 1, "autoplay": 1, "ugc_pay": 0, "is_cooperation": 0, "ugc_pay_preview": 0, "no_background": 0, "arc_pay": 0, "pay_free_watch": 0}, "owner": {"mid": 25876945, "name": "极客湾Geekerwan", "face": "http://i1.hdslb.com/bfs/face/d0f7a7ee34a4a45c8390eb3a07e4d7f2d70bae91.jpg"}, "stat": {"aid": 280496928, "view": 1725406, "danmaku": 4874, "reply": 5752, "favorite": 12049, "coin": 17512, "share": 6363, "now_rank": 0, "his_rank": 89, "like": 86494, "dislike": 0, "vt": 0, "vv": 1725406}, "dynamic": "", "cid": 1319125259, "dimension": {"width": 3840, "height": 2160, "rotate": 0}, "short_link_v2": "https://b23.tv/BV1ec41197F6", "first_frame": "http://i0.hdslb.com/bfs/storyff/n231102sa36xrsv0wnyiuc138l6z9qt3_firsti.jpg", "pub_location": "上海", "cover43": "", "bvid": "BV1ec41197F6", "season_type": 0, "is_ogv": false, "ogv_info": null, "enable_vt": 0, "ai_rcmd": null, "rcmd_reason": "新一代的通信技术——星闪"}, {"aid": 365161358, "videos": 1, "tid": 138, "tname": "搞笑", "copyright": 1, "pic": "http://i1.hdslb.com/bfs/archive/f98fe9b0c0a494baa545f4863a62d75fa04c25cd.jpg", "title": "《一种新的聊天方式》", "pubdate": 1698322037, "ctime": 1698322037, "desc": "-", "state": 0, "duration": 118, "mission_id": 4006050, "rights": {"bp": 0, "elec": 0, "download": 0, "movie": 0, "pay": 0, "hd5": 0, "no_reprint": 1, "autoplay": 1, "ugc_pay": 0, "is_cooperation": 0, "ugc_pay_preview": 0, "no_background": 0, "arc_pay": 0, "pay_free_watch": 0}, "owner": {"mid": 444959794, "name": "不会聊天的小七", "face": "https://i1.hdslb.com/bfs/face/801cd9fccc0f38c4320552de123572d4bc28ddb2.jpg"}, "stat": {"aid": 365161358, "view": 4133256, "danmaku": 1561, "reply": 1525, "favorite": 39961, "coin": 30506, "share": 29171, "now_rank": 0, "his_rank": 41, "like": 310692, "dislike": 0, "vt": 0, "vv": 4133256}, "dynamic": "", "cid": 1311942440, "dimension": {"width": 1440, "height": 1080, "rotate": 0}, "season_id": 952574, "short_link_v2": "https://b23.tv/BV1J94y1j7wH", "up_from_v2": 35, "first_frame": "http://i1.hdslb.com/bfs/storyff/n231026sa1xwquoxdrqev43q55trb974_firsti.jpg", "pub_location": "四川", "cover43": "", "bvid": "BV1J94y1j7wH", "season_type": 0, "is_ogv": false, "ogv_info": null, "enable_vt": 0, "ai_rcmd": null, "rcmd_reason": "教你用音乐追债"}, {"aid": 705235987, "videos": 1, "tid": 228, "tname": "人文历史", "copyright": 1, "pic": "http://i1.hdslb.com/bfs/archive/d9d27bbc1a34dbb6b52aafa7b3470c4ac5a68ce7.jpg", "title": "“天下一统”背后隐藏的“惊天动机”！「三国归晋」", "pubdate": 1698389999, "ctime": 1698389999, "desc": "让司马家臭名昭著，为曹魏续命五年的“奋力一击”！「天子之血」\n一计害三贤？三大名将之死的幕后黑手到底是谁？「成都之乱」\n“天下归一”背后隐藏的“惊天动机”！「三国归晋」", "state": 0, "duration": 2523, "rights": {"bp": 0, "elec": 0, "download": 0, "movie": 0, "pay": 0, "hd5": 1, "no_reprint": 1, "autoplay": 1, "ugc_pay": 0, "is_cooperation": 0, "ugc_pay_preview": 0, "no_background": 0, "arc_pay": 0, "pay_free_watch": 0}, "owner": {"mid": 35762548, "name": "勇敢De永", "face": "https://i1.hdslb.com/bfs/face/63b5f99b9642a424ea7ea8d83e36fff9209b719d.jpg"}, "stat": {"aid": 705235987, "view": 6430081, "danmaku": 8142, "reply": 1960, "favorite": 55981, "coin": 37787, "share": 3140, "now_rank": 0, "his_rank": 50, "like": 143299, "dislike": 0, "vt": 0, "vv": 6430081}, "dynamic": "", "cid": 1312452996, "dimension": {"width": 4320, "height": 2160, "rotate": 0}, "season_id": 2036030, "short_link_v2": "https://b23.tv/BV1nQ4y1H7Eb", "first_frame": "http://i1.hdslb.com/bfs/storyff/n231027sa2ktar418z03s731726dskor_firsti.jpg", "pub_location": "山西", "cover43": "", "bvid": "BV1nQ4y1H7Eb", "season_type": 0, "is_ogv": false, "ogv_info": null, "enable_vt": 0, "ai_rcmd": null, "rcmd_reason": "乱而神秘的迷人历史故事"}, {"aid": 790153801, "videos": 1, "tid": 233, "tname": "极客DIY", "copyright": 1, "pic": "http://i0.hdslb.com/bfs/archive/1c2d67658025250949d6c432aa549bc16266bd28.jpg", "title": "【修一j】成功把蜥蜴标本复活成了冰霜骨龙！", "pubdate": 1698463800, "ctime": 1698428819, "desc": "死灵法师的最新召唤兽噢~", "state": 0, "duration": 484, "rights": {"bp": 0, "elec": 0, "download": 0, "movie": 0, "pay": 0, "hd5": 1, "no_reprint": 1, "autoplay": 1, "ugc_pay": 0, "is_cooperation": 0, "ugc_pay_preview": 0, "no_background": 0, "arc_pay": 0, "pay_free_watch": 0}, "owner": {"mid": 9030440, "name": "修一j", "face": "https://i2.hdslb.com/bfs/face/6b20ece9a251eff0d12625f02258d370c52e7fe3.jpg"}, "stat": {"aid": 790153801, "view": 1899105, "danmaku": 1666, "reply": 1271, "favorite": 48600, "coin": 41027, "share": 4141, "now_rank": 0, "his_rank": 0, "like": 83143, "dislike": 0, "vt": 0, "vv": 1899105}, "dynamic": "死灵法师的最新召唤兽噢~有下饭环节，请注意！", "cid": 1313256558, "dimension": {"width": 3840, "height": 2160, "rotate": 0}, "season_id": 38683, "short_link_v2": "https://b23.tv/BV1ay4y1w7x1", "first_frame": "http://i0.hdslb.com/bfs/storyff/n231028sa2y3xtm2phzp38dvbdlifp2k_firsti.jpg", "pub_location": "四川", "cover43": "", "bvid": "BV1ay4y1w7x1", "season_type": 0, "is_ogv": false, "ogv_info": null, "enable_vt": 0, "ai_rcmd": null, "rcmd_reason": "准备好复活仪式了吗？"}, {"aid": 235218136, "videos": 4, "tid": 172, "tname": "手机游戏", "copyright": 1, "pic": "http://i2.hdslb.com/bfs/archive/5304909e9b4d037fba93ca833d15c823ec9ee41d.png", "title": "《明日方舟》限定干员「塑心」前瞻PV", "pubdate": 1698462000, "ctime": 1698460294, "desc": "《明日方舟》限定干员「塑心」前瞻PV\n\n在终点到来之前，\n请让我为您奏响我自己", "state": 0, "duration": 462, "rights": {"bp": 0, "elec": 0, "download": 0, "movie": 0, "pay": 0, "hd5": 1, "no_reprint": 0, "autoplay": 1, "ugc_pay": 0, "is_cooperation": 0, "ugc_pay_preview": 0, "no_background": 0, "arc_pay": 0, "pay_free_watch": 0}, "owner": {"mid": 161775300, "name": "明日方舟", "face": "https://i0.hdslb.com/bfs/face/d4005a0f9b898d8bb049caf9c6355f8e8f772a8f.jpg"}, "stat": {"aid": 235218136, "view": 1094228, "danmaku": 8488, "reply": 3927, "favorite": 15241, "coin": 26616, "share": 11440, "now_rank": 0, "his_rank": 54, "like": 92209, "dislike": 0, "vt": 0, "vv": 1094228}, "dynamic": "", "cid": 1325499947, "dimension": {"width": 1920, "height": 1080, "rotate": 0}, "short_link_v2": "https://b23.tv/BV1We41197Tc", "up_from_v2": 2, "first_frame": "http://i2.hdslb.com/bfs/storyff/n231108saotdylfaea4bofy4hc86s8mp_firsti.jpg", "pub_location": "上海", "cover43": "", "bvid": "BV1We41197Tc", "season_type": 0, "is_ogv": false, "ogv_info": null, "enable_vt": 0, "ai_rcmd": null, "rcmd_reason": "在终点到来之前， 请让我为您奏响我自己"}, {"aid": 535117474, "videos": 1, "tid": 31, "tname": "翻唱", "copyright": 1, "pic": "http://i1.hdslb.com/bfs/archive/0191ff76859c42330088c7759a77742c9aac8aa8.jpg", "title": "最震撼的一集！花腔吟唱《斯卡布罗集市》|“他将是我最挚爱之人”『说说Crystal·翻唱』", "pubdate": 1698073104, "ctime": 1698073105, "desc": "《斯卡布罗集市》\n原唱：Sarah Brightman\n翻唱：说说Crystal\n混音：dr_eeee\n\n好的音乐会治愈自己，录完之后整个人像置身美丽的大自然身心舒畅且平静，这首歌被莎拉·布莱曼发挥到了超神的境界，感叹这样的演唱境界，这就是来自上天的馈赠吧。录制的时候几近怀疑人生，那种浑然天成的天神般的嗓音真的不可思议，美哭了。我自己尝试着在间奏的地方加入了一段自己编的美声吟唱，最后完成的时候还是非常满意，只能说艺术无止境，认真品味的时候只有满满的惭愧，但是希望你们听到这样的美丽！\n\n不知道你们有没有这样", "state": 0, "duration": 262, "mission_id": 1521552, "rights": {"bp": 0, "elec": 0, "download": 0, "movie": 0, "pay": 0, "hd5": 0, "no_reprint": 1, "autoplay": 1, "ugc_pay": 0, "is_cooperation": 0, "ugc_pay_preview": 0, "no_background": 0, "arc_pay": 0, "pay_free_watch": 0}, "owner": {"mid": 283886865, "name": "说说Crystal", "face": "https://i0.hdslb.com/bfs/face/336134aa6bd431ec9530f2f5e61a389f68382355.jpg"}, "stat": {"aid": 535117474, "view": 1608581, "danmaku": 811, "reply": 2253, "favorite": 81419, "coin": 61019, "share": 7812, "now_rank": 0, "his_rank": 59, "like": 122365, "dislike": 0, "vt": 0, "vv": 1608581}, "dynamic": "你要去斯卡布罗集市吗？", "cid": 1308993596, "dimension": {"width": 1920, "height": 1080, "rotate": 0}, "short_link_v2": "https://b23.tv/BV1HM411X7aT", "first_frame": "http://i2.hdslb.com/bfs/storyff/n231023sa3jv0au7v1k2aq32xo3hr97s_firsti.jpg", "pub_location": "四川", "cover43": "", "bvid": "BV1HM411X7aT", "season_type": 0, "is_ogv": false, "ogv_info": null, "enable_vt": 0, "ai_rcmd": null, "rcmd_reason": "听UP的歌声可以闻到植物和花香"}, {"aid": 705271318, "videos": 1, "tid": 31, "tname": "翻唱", "copyright": 1, "pic": "http://i2.hdslb.com/bfs/archive/f2e009a180401cce01b7b3875bd084bbb640777f.jpg", "title": "小时候听不懂…那现在呢？《其实都没有》", "pubdate": 1698809400, "ctime": 1698771555, "desc": "《其实都没有》\n原唱：杨宗纬\n翻唱：咻咻满\n混音：Riraru\n校对：艾莉Anicca", "state": 0, "duration": 227, "mission_id": 1521552, "rights": {"bp": 0, "elec": 0, "download": 0, "movie": 0, "pay": 0, "hd5": 0, "no_reprint": 1, "autoplay": 1, "ugc_pay": 0, "is_cooperation": 0, "ugc_pay_preview": 0, "no_background": 0, "arc_pay": 0, "pay_free_watch": 0}, "owner": {"mid": 37754047, "name": "咻咻满", "face": "https://i1.hdslb.com/bfs/face/1539ed33d13fcc6f085f61c634d9617814e187f0.jpg"}, "stat": {"aid": 705271318, "view": 1358442, "danmaku": 946, "reply": 1745, "favorite": 16685, "coin": 32220, "share": 3089, "now_rank": 0, "his_rank": 0, "like": 54645, "dislike": 0, "vt": 0, "vv": 1358442}, "dynamic": "唱一下最近大家呼声比较高的《其实都没有》！不知不觉这歌都十年了......", "cid": 1317512082, "dimension": {"width": 1920, "height": 1080, "rotate": 0}, "short_link_v2": "https://b23.tv/BV1YQ4y1H7w7", "first_frame": "http://i0.hdslb.com/bfs/storyff/n231101sa188pm4qp1ecdp1o7xnvg1tp_firsti.jpg", "pub_location": "福建", "cover43": "", "bvid": "BV1YQ4y1H7w7", "season_type": 0, "is_ogv": false, "ogv_info": null, "enable_vt": 0, "ai_rcmd": null, "rcmd_reason": "年少不知曲中意，再听已是曲中人"}, {"aid": 277530958, "videos": 1, "tid": 159, "tname": "时尚潮流", "copyright": 1, "pic": "http://i0.hdslb.com/bfs/archive/0007d0a70cfd5d7a0cbaf398308ba89f35d49f82.jpg", "title": "前任总裁阴阳怪气！时装评论人实名开怼！祝他成功吧！深度解析「GUCCI 古驰 2024春夏女装秀场」", "pubdate": 1698206400, "ctime": 1698161230, "desc": "员工骂人，老板道歉，真的是一场好戏呀！\n\n每周三、周六中午12点，咱们不见不散！\n\n欢迎来骚扰我们：\n\n新浪微博：lolo-may/aha没有事业线\n\nYouTube： AHALOLO", "state": 0, "duration": 1184, "mission_id": 4006165, "rights": {"bp": 0, "elec": 0, "download": 0, "movie": 0, "pay": 0, "hd5": 0, "no_reprint": 1, "autoplay": 1, "ugc_pay": 0, "is_cooperation": 0, "ugc_pay_preview": 0, "no_background": 0, "arc_pay": 0, "pay_free_watch": 0}, "owner": {"mid": 353368172, "name": "AHALOLO", "face": "https://i2.hdslb.com/bfs/face/03e81799ea2390af3f5c4b9572ad75d622f16354.jpg"}, "stat": {"aid": 277530958, "view": 575006, "danmaku": 2466, "reply": 784, "favorite": 2188, "coin": 8482, "share": 500, "now_rank": 0, "his_rank": 0, "like": 20580, "dislike": 0, "vt": 0, "vv": 575006}, "dynamic": "他带得出冠军吗？！", "cid": 1310106296, "dimension": {"width": 1920, "height": 1080, "rotate": 0}, "short_link_v2": "https://b23.tv/BV1rw411F7HJ", "first_frame": "http://i1.hdslb.com/bfs/storyff/n231024sa2f7khthpbnx4g14gzkkfm6v_firsti.jpg", "pub_location": "江苏", "cover43": "", "bvid": "BV1rw411F7HJ", "season_type": 0, "is_ogv": false, "ogv_info": null, "enable_vt": 0, "ai_rcmd": null, "rcmd_reason": "GUCCI女装风格大变背后的原因是什么"}]}}